{
  "config": {
    "feature": {
      "config": {
        "feature": {
          "config": {
            "feature": {
              "config": {
                "target": {
                  "block": "minecraft:gravel",
                  "probability": 0.9,
                  "predicate_type": "minecraft:random_block_match"
                },
                "state": {
                  "Name": "minecraft:mossy_cobblestone"
                },
                "size": 28
              },
              "type": "minecraft:ore"
            },
            "decorator": {
              "config": {
                "bottom_offset": 65,
                "top_offset": 0,
                "maximum": 14
              },
              "type": "minecraft:range"
            }
          },
          "type": "minecraft:decorated"
        },
        "decorator": {
          "config": {},
          "type": "minecraft:square"
        }
      },
      "type": "minecraft:decorated"
    },
    "decorator": {
      "config": {
        "count": 32
      },
      "type": "minecraft:count"
    }
  },
  "type": "minecraft:decorated"
}